[
    {
        "Id": 1,
        "name": "Md. Mahafuzul Islam Samuel",
        "expert": "Medicine-Epecialist",
        "department": "Eye",
        "time": "10:00am-8:00pm",
        "call": "01716458935",
        "img": "https://media.istockphoto.com/photos/happy-healthcare-practitioner-picture-id138205019?k=20&m=138205019&s=612x612&w=0&h=KpsSMVsplkOqTnAJmOye4y6DcciVYIBe5dYDgYXLVW4="
    },
    {
        "Id": 2,
        "name": "Bikash Mojumder",
        "expert": "Child Specialist",
        "department": "Medicine",
        "time": "10:00am-8:00pm",
        "call": "01587925478",
        "img": "https://st.depositphotos.com/2309453/2582/i/950/depositphotos_25820415-stock-photo-male-doctor-with-arms-crossed.jpg"
    },
    {
        "Id": 3,
        "name": "Alhaz Shajahan Newaz",
        "expert": "Eye Specialist",
        "department": "Sex",
        "time": "10:00am-8:00pm",
        "call": "01987456321",
        "img": "https://media.istockphoto.com/photos/never-fear-the-doctor-is-here-picture-id507954725?k=20&m=507954725&s=612x612&w=0&h=8i95b60DdEu5SWUTzylXzRF-blhfthg5tfqp9xU1Z_g="
    },
    {
        "Id": 4,
        "name": "Baharam Uddin",
        "expert": "Surgeon",
        "department": "Dental",
        "time": "10:00am-8:00pm",
        "call": "01789654123",
        "img": "https://img.freepik.com/free-photo/portrait-hansome-young-male-doctor-man_171337-5068.jpg?size=626&ext=jpg"
    },
    {
        "Id": 5,
        "name": "Tofayel Ahamed",
        "expert": "Surgeon",
        "department": "Head",
        "time": "10:00am-8:00pm",
        "call": "0654789321",
        "img": "https://orlandohandsurgery.com/wp-content/uploads/2016/01/DrBrianWhite_website-1024x748-white-bkgd-670x500-1-e1552586868880.jpg"
    },
    {
        "Id": 6,
        "name": "Md Jamirul Islam",
        "expert": "Cardiologist",
        "department": "Cardiac",
        "time": "10:00am-8:00pm",
        "call": "01321456987",
        "img": "https://cdn.crello.com/api/media/medium/135128856/stock-photo-male-doctor-with-stethoscope"
    }

]